[
    {
        "name": "TalkSport - Simon/Jordan",
        "source_uu_id": "UUWw6scNyopJ0yjMu1SyOEyw",
        "target_playlist": "PLoJvzSXcA7j_VONfig9ZksTPYN9Nz090V",
        "keywords": [
            "Jordan",
            "Simon"
        ],
        "purge_after_days": 10
    },
    {
        "name": "TalkSport - Darren Bent",
        "source_uu_id": "UUWw6scNyopJ0yjMu1SyOEyw",
        "target_playlist": "PLoJvzSXcA7j-NvCUml49Ogaa8R49a5rUp",
        "keywords": [
            "Bent",
            "Darren"
        ],
        "purge_after_days": 10
    },
    {
        "name": "WhistlinDiesel",
        "source_uu_id": "UUdqp0KK_Io7TwK5cJMBvB0Q",
        "target_playlist": "PLoJvzSXcA7j_wyNY5w2sVihebIit2ma-H",
        "keywords": [
            ""
        ],
        "purge_after_days": 14
    },
    {
        "name": "I Did A Thing",
        "source_uu_id": "UUJLZe_NoiG0hT7QCX_9vmqw",
        "target_playlist": "PLoJvzSXcA7j_wyNY5w2sVihebIit2ma-H",
        "keywords": [
            ""
        ],
        "purge_after_days": 14
    },
    {
        "name": "The Boyscast",
        "source_uu_id": "UUzKFvBRI6VT3jYJq6a820nA",
        "target_playlist": "PLoJvzSXcA7j_wyNY5w2sVihebIit2ma-H",
        "keywords": [
            "Episode"
        ],
        "purge_after_days": 14
    },
    {
        "name": "Danny Polishchuk Comedy",
        "source_uu_id": "UUh8IVqYrB-fng2R0digXN7A",
        "target_playlist": "PLoJvzSXcA7j_wyNY5w2sVihebIit2ma-H",
        "keywords": [
            "Low",
            "value",
            "male"
        ],
        "purge_after_days": 7
    }
]